bf_engine/__init__.py
bf_engine/api.py
bf_engine/config.py
bf_engine/logger.py
bf_engine/util.py
bf_engine/caller/__init__.py
bf_engine/caller/act_caller.py
bf_engine/caller/base.py
bf_engine/caller/chat_caller.py
bf_engine/caller/common_service_caller.py
bf_engine/caller/config_manager_caller.py
bf_engine/caller/dialogue_manager_caller.py
bf_engine/caller/intent_caller.py
bf_engine/caller/knowledge_caller.py
bf_engine/caller/langconv.py
bf_engine/caller/parser_caller.py
bf_engine/caller/qa_caller.py
bf_engine/caller/set_config.py
bf_engine/caller/skill_service_caller.py
bf_engine/caller/statistci_caller.py
bf_engine/caller/zh_wiki.py
bf_engine/core/__init__.py
bf_engine/core/bot.py
bf_engine/core/chat_service.py
bf_engine/core/common_service.py
bf_engine/core/config_manager.py
bf_engine/core/dialogue_act.py
bf_engine/core/dialogue_manager.py
bf_engine/core/intent_answering.py
bf_engine/core/knowledge_graph.py
bf_engine/core/log_statistic.py
bf_engine/core/module.py
bf_engine/core/ner_parser.py
bf_engine/core/question_answering.py
bf_engine/core/set.py
bf_engine/core/skill_service.py
bf_engine/core/task_engine.py
bf_engine/core/test.py
bf_engine/data/default_dm.json
bf_engine/data/语料上传模板.xlsx
bf_engine/data/问答上传模板.xlsx
bf_engine/entity/__init__.py
bf_engine/entity/answer.py
bf_engine/entity/enums.py
bf_engine/entity/exception.py
bf_engine/utils/__init__.py
bf_engine/utils/local_cache.py
bf_engine/utils/request_form_data.py
bfengine-0.1.145.dist-info/METADATA
bfengine-0.1.145.dist-info/WHEEL
bfengine-0.1.145.dist-info/top_level.txt
bfengine-0.1.145.dist-info/RECORD
