Metadata-Version: 2.1
Name: bfengine
Version: 0.1.145
Summary: bf engine sdk for python
Home-page: UNKNOWN
Author: JeremyXin
Author-email: chengjiexin@emotibot.com
License: UNKNOWN
Platform: UNKNOWN
Classifier: Programming Language :: Python :: 3
Classifier: License :: OSI Approved :: MIT License
Classifier: Operating System :: OS Independent
Requires-Python: >=3.6
Requires-Dist: requests
Requires-Dist: tqdm
